airbrake_integrations/__about__.py
airbrake_integrations/__init__.py
airbrake_integrations/django/__init__.py
airbrake_integrations/django/decorators.py
airbrake_integrations/django/middleware.py
airbrake_integrations/flask/__init__.py
airbrake_integrations/flask/app.py
airbrake_integrations/twisted/__init__.py
airbrake_integrations/twisted/observer.py
tests/django/__init__.py
tests/django/conf.py
tests/django/test_logger.py
tests/django/test_middleware.py
tests/flask/__init__.py
tests/flask/flask_test.py
tests/twisted/__init__.py
tests/twisted/test_twisted.py
airbrake_integrations-0.1.4.dist-info/METADATA
airbrake_integrations-0.1.4.dist-info/WHEEL
airbrake_integrations-0.1.4.dist-info/top_level.txt
airbrake_integrations-0.1.4.dist-info/RECORD
