Metadata-Version: 2.1
Name: airbrake-integrations
Version: 0.1.4
Summary: Python Integrations for airbrake.io
Home-page: https://github.com/airbrake/airbrake-python-integrations
Author: Zach Goldstein
Author-email: zach@airbrake.io
License: Apache License, Version 2.0
Keywords: airbrake exceptions airbrake.io 176e0a6f
Platform: UNKNOWN
Classifier: Intended Audience :: Developers
Classifier: License :: OSI Approved :: Apache Software License
Classifier: Operating System :: OS Independent
Classifier: Topic :: Software Development
Classifier: Framework :: Django
Classifier: Environment :: Web Environment
Classifier: Programming Language :: Python
Classifier: Programming Language :: Python :: 2
Classifier: Programming Language :: Python :: 2.7
Classifier: Programming Language :: Python :: 3
Classifier: Programming Language :: Python :: 3.3
Classifier: Programming Language :: Python :: 3.4
Classifier: Programming Language :: Python :: 3.5
Classifier: Programming Language :: Python :: Implementation :: CPython
Requires-Dist: requests (>=2.20.0)
